Workbook
Name aporte: API!$D$17
Name patrimonio: API!$D$20
Name qtd_anos: API!$D$18
Name rendimento_carteira: API!$D$13
Name salario: API!$D$12
Name sugestao_investimento: API!$D$14
Name taxa_mensal: API!$D$19

Sheet API
B11: CONFIGURAÇÕES
B12: Salário | D12: 2000
B13: Rendimento Carteira | D13: 0.01
B14: Sugestão de Investimento (30%) | D14: =$D$12*30% -> 600
B16: INVESTIMENTO MENSAL
B17: Quanto Investir Por Mês ? > | D17: 700
B18: Por Quantos Anos ? > | D18: 5
B19: Taxa de Rendimento Mensal ? | D19: 0.01079
B20: Patrimônio Acumulado ? | D20: =FV(taxa_mensal,qtd_anos*12,aporte*-1) -> 58643.84
B21: Dividendos Mensais ? | D21: =patrimonio*rendimento_carteira -> 586.4384
B23: CENÁRIOS | D23: Dividendo
A24: 2 | B24: Quanto em 2 Anos ? | C24: =FV($D$19,$A24*12,$D$17*-1) -> 19059.339 | D24: =$C24*rendimento_carteira -> 190.59339
A25: 5 | B25: Quanto em 5 Anos ? | C25: =FV($D$19,$A25*12,$D$17*-1) -> 58643.84 | D25: =$C25*rendimento_carteira -> 586.4384
A26: 10 | B26: Quanto em 10 Anos ? | C26: =FV($D$19,$A26*12,$D$17*-1) -> 170298.95 | D26: =$C26*rendimento_carteira -> 1702.9895
A27: 20 | B27: Quanto em 20 Anos ? | C27: =FV($D$19,$A27*12,$D$17*-1) -> 787638.88 | D27: =$C27*rendimento_carteira -> 7876.3888
A28: 30 | B28: Quanto em 30 Anos ? | C28: =FV($D$19,$A28*12,$D$17*-1) -> 3025518.8 | D28: =$C28*rendimento_carteira -> 30255.188
B32: PERFIL | C32: AGRESSIVO
B33: VALOR A SER INVESTIDO POR MÊS > | C33: =aporte -> 700
B35: TIPOS DE FII | C35: Percentual Sugerido | D35: Valores
B36: PAPEL | C36: =VLOOKUP($C$32&"-"&B36,Chave!$A:$D,4,FALSE) -> 0.5 | D36: =C36*$C$33 -> 350
B37: TIJOLO | C37: =VLOOKUP($C$32&"-"&B37,Chave!$A:$D,4,FALSE) -> 0.1 | D37: =C37*$C$33 -> 70
B38: HÍBRIDOS | C38: =VLOOKUP($C$32&"-"&B38,Chave!$A:$D,4,FALSE) -> 0.05 | D38: =C38*$C$33 -> 35
B39: FOFs | C39: =VLOOKUP($C$32&"-"&B39,Chave!$A:$D,4,FALSE) -> 0.05 | D39: =C39*$C$33 -> 35
B40: DESENVOLVIMENTO | C40: =VLOOKUP($C$32&"-"&B40,Chave!$A:$D,4,FALSE) -> 0.2 | D40: =C40*$C$33 -> 140
B41: HOTELARIAS | C41: =VLOOKUP($C$32&"-"&B41,Chave!$A:$D,4,FALSE) -> 0.1 | D41: =C41*$C$33 -> 70
D42: =SUM(D36:D41) -> 700

Sheet Chave
A2: CHAVE | B2: PERFIL | C2: TIPO DE FII | D2: %
A3: =B3&"-"&C3 -> CONSERVADOR-PAPEL | B3: CONSERVADOR | C3: PAPEL | D3: 0.3
A4: =B4&"-"&C4 -> CONSERVADOR-TIJOLO | B4: CONSERVADOR | C4: TIJOLO | D4: 0.5
A5: =B5&"-"&C5 -> CONSERVADOR-HÍBRIDOS | B5: CONSERVADOR | C5: HÍBRIDOS | D5: 0.1
A6: =B6&"-"&C6 -> CONSERVADOR-FOFs | B6: CONSERVADOR | C6: FOFs | D6: 0.1
A7: =B7&"-"&C7 -> CONSERVADOR-DESENVOLVIMENTO | B7: CONSERVADOR | C7: DESENVOLVIMENTO | D7: 0
A8: =B8&"-"&C8 -> CONSERVADOR-HOTELARIAS | B8: CONSERVADOR | C8: HOTELARIAS | D8: 0
A9: =B9&"-"&C9 -> MODERADO-PAPEL | B9: MODERADO | C9: PAPEL | D9: 0.32
A10: =B10&"-"&C10 -> MODERADO-TIJOLO | B10: MODERADO | C10: TIJOLO | D10: 0.35
A11: =B11&"-"&C11 -> MODERADO-HÍBRIDOS | B11: MODERADO | C11: HÍBRIDOS | D11: 0.08
A12: =B12&"-"&C12 -> MODERADO-FOFs | B12: MODERADO | C12: FOFs | D12: 0.05
A13: =B13&"-"&C13 -> MODERADO-DESENVOLVIMENTO | B13: MODERADO | C13: DESENVOLVIMENTO | D13: 0.1
A14: =B14&"-"&C14 -> MODERADO-HOTELARIAS | B14: MODERADO | C14: HOTELARIAS | D14: 0.1
... A20: =B20&"-"&C20 -> AGRESSIVO-HOTELARIAS | B20: AGRESSIVO | C20: HOTELARIAS | D20: 0.1
